PPTT/__init__.py
PPTT/__main__.py
PPTT/cli.py
PPTT/ppt.py
PPTT/type.py
PPTT/utils.py
PPTT/replace/__init__.py
PPTT/replace/handler.py
PPTT/replace/stub.py
tests/data_replace/__init__.py
tests/data_replace/test_chart_replace_mode.py
tests/data_replace/test_delete_slide.py
tests/data_replace/test_font_replace.py
tests/data_replace/test_replace_mode.py
tests/data_replace/testcase.py
PPTT-0.0.9.dist-info/LICENSE
PPTT-0.0.9.dist-info/METADATA
PPTT-0.0.9.dist-info/WHEEL
PPTT-0.0.9.dist-info/entry_points.txt
PPTT-0.0.9.dist-info/top_level.txt
PPTT-0.0.9.dist-info/RECORD
