Metadata-Version: 2.1
Name: PPTT
Version: 0.0.9
Summary: PowerPoint Template for python
Home-page: https://github.com/spaceone-dev/PPTT
Maintainer: MEGAZONE SpaceONE Team
Maintainer-email: admin@spaceone.dev
License: Apache License 2.0
Platform: UNKNOWN
Classifier: Intended Audience :: Developers
Classifier: Operating System :: OS Independent
Classifier: Programming Language :: Python
Classifier: Programming Language :: Python :: 3
Classifier: Programming Language :: Python :: 3 :: Only
Classifier: Programming Language :: Python :: 3.8
Classifier: Topic :: Software Development :: Libraries :: Python Modules
Requires-Python: >=3.8
Requires-Dist: python-pptx (==0.6.18)
Requires-Dist: click (>=7.1.2)
Requires-Dist: ast-decompiler (==0.4.0)
Requires-Dist: python-slugify (==4.0.1)
Requires-Dist: dacite (==1.5.1)
